apamaeventparser/__init__.py
apamaeventparser/apamaevent.py
apamaeventparser/eventparser.py
apamaeventparser-0.9.0.dist-info/DESCRIPTION.rst
apamaeventparser-0.9.0.dist-info/METADATA
apamaeventparser-0.9.0.dist-info/RECORD
apamaeventparser-0.9.0.dist-info/WHEEL
apamaeventparser-0.9.0.dist-info/metadata.json
apamaeventparser-0.9.0.dist-info/top_level.txt
