Metadata-Version: 2.0
Name: apamaeventparser
Version: 0.9.0
Summary: A parser for apama events
Home-page: https://github.com/DanskeBank/apamaeventparser
Author: Adam Britt
Author-email: adb@danskebank.dk
License: MIT
Keywords: epl parsing events
Platform: UNKNOWN
Classifier: Development Status :: 3 - Alpha
Classifier: Intended Audience :: Developers
Classifier: Topic :: Software Development :: Libraries
Classifier: License :: OSI Approved :: MIT License
Classifier: Programming Language :: Python :: 2.7
Classifier: Programming Language :: Python :: 3.5
Requires-Dist: funcparserlib
